fastkv/__init__.py
fastkv/__main__.py
fastkv/fastkv.py
fastkv-0.1.0.dist-info/licenses/LICENCE
fastkv-0.1.0.dist-info/METADATA
fastkv-0.1.0.dist-info/WHEEL
fastkv-0.1.0.dist-info/top_level.txt
fastkv-0.1.0.dist-info/RECORD
