Metadata-Version: 2.4
Name: fastkv
Version: 0.1.0
Summary: A super fast filesystem-based key-value store.
Author-email: Arif Chowdhury <arifchy369@protonmail.com>
License: MIT
Project-URL: Homepage, https://github.com/arifchy369/FastKV
Project-URL: Repository, https://github.com/arifchy369/FastKV
Project-URL: Issues, https://github.com/arifchy369/FastKV/issues
Keywords: database,kv-store,fastkv,storage,files,msgpack
Requires-Python: >=3.8
License-File: LICENCE
Requires-Dist: msgpack>=1.0.0
Dynamic: license-file
